tflab/__init__.py
tflab/cost_functions.py
tflab/network.py
tflab/optimizers.py
tflab/serializable.py
tflab/utils.py
tflab/word2vec.py
tflab-0.1.3.data/scripts/run_mmd.py
tflab-0.1.3.data/scripts/run_network.py
tflab-0.1.3.data/scripts/run_word2vec.py
tflab-0.1.3.dist-info/DESCRIPTION.rst
tflab-0.1.3.dist-info/METADATA
tflab-0.1.3.dist-info/RECORD
tflab-0.1.3.dist-info/WHEEL
tflab-0.1.3.dist-info/metadata.json
tflab-0.1.3.dist-info/top_level.txt
