Metadata-Version: 2.0
Name: tflab
Version: 0.1.3
Summary: A laboratory for experimenting with Tensorflow abstraction
Home-page: https://github.com/mhamilton723/tflab
Author: Mark Hamilton
Author-email: mhamilton723@gmail.com
License: UNKNOWN
Platform: UNKNOWN
Requires-Dist: numpy
Requires-Dist: tensorflow
